amplo/__init__.py
amplo/pipeline.py
amplo/training.py
amplo/validation.py
amplo/api/__init__.py
amplo/api/_base.py
amplo/api/databricks.py
amplo/api/platform.py
amplo/api/storage.py
amplo/automl/__init__.py
amplo/automl/data_processing.py
amplo/automl/grid_search.py
amplo/automl/modelling.py
amplo/automl/standardization.py
amplo/automl/feature_processing/__init__.py
amplo/automl/feature_processing/_base.py
amplo/automl/feature_processing/feature_aggregator.py
amplo/automl/feature_processing/feature_processing.py
amplo/automl/feature_processing/feature_selection.py
amplo/automl/feature_processing/nop_feature_extractor.py
amplo/automl/feature_processing/pooling.py
amplo/automl/feature_processing/score_watcher.py
amplo/automl/feature_processing/static_feature_extractor.py
amplo/automl/feature_processing/temporal_feature_extractor.py
amplo/automl/feature_processing/wavelet_extractor.py
amplo/base/__init__.py
amplo/base/exceptions.py
amplo/base/objects.py
amplo/classification/__init__.py
amplo/classification/_base.py
amplo/classification/catboost.py
amplo/classification/lgbm.py
amplo/classification/partial_boosting.py
amplo/classification/stacking.py
amplo/classification/xgb.py
amplo/observation/__init__.py
amplo/observation/_base.py
amplo/observation/data.py
amplo/observation/model.py
amplo/regression/__init__.py
amplo/regression/_base.py
amplo/regression/catboost.py
amplo/regression/lgbm.py
amplo/regression/partial_boosting.py
amplo/regression/stacking.py
amplo/regression/xgb.py
amplo/utils/__init__.py
amplo/utils/data.py
amplo/utils/io.py
amplo/utils/json.py
amplo/utils/logging.py
amplo/utils/metrics.py
amplo/utils/sys.py
amplo/utils/util.py
tests/__init__.py
tests/conftest.py
tests/test_models.py
tests/test_pipeline.py
tests/api/__init__.py
tests/api/test_databricks.py
tests/api/test_platform.py
tests/automl/__init__.py
tests/automl/test_data_processor.py
tests/automl/test_modelling.py
tests/automl/test_standardizer.py
tests/automl/feature_processing/__init__.py
Amplo-0.17.0.dist-info/LICENSE
Amplo-0.17.0.dist-info/METADATA
Amplo-0.17.0.dist-info/WHEEL
Amplo-0.17.0.dist-info/top_level.txt
Amplo-0.17.0.dist-info/RECORD
