Metadata-Version: 2.1
Name: Amplo
Version: 0.17.0
Summary: Fully automated end to end machine learning pipeline
Home-page: https://github.com/nielsuit227/AutoML
Author: Amplo AG
Author-email: info@amplo.ch
Classifier: Programming Language :: Python :: 3
Classifier: License :: OSI Approved :: GNU General Public License v3 (GPLv3)
Classifier: Operating System :: OS Independent
Requires-Python: >=3.9
License-File: LICENSE
Requires-Dist: azure-core (>=1.23.1)
Requires-Dist: azure-storage-blob (>=12.11.0)
Requires-Dist: catboost (>=1.0.0)
Requires-Dist: cleanlab (>=2.0.0)
Requires-Dist: colorlog (>=6.6.0)
Requires-Dist: joblib (>=1.1.0)
Requires-Dist: lightgbm (>=3.3.1)
Requires-Dist: numba (>=0.55.0)
Requires-Dist: numpy (<1.23,>=1.21.4)
Requires-Dist: optuna (<3.1.0,>=3.0.0)
Requires-Dist: pandas (>=1.5.0)
Requires-Dist: polars (==0.15.8)
Requires-Dist: pyarrow (>=9.0.0)
Requires-Dist: pytest (>=7.1.1)
Requires-Dist: pywavelets (>=1.3.0)
Requires-Dist: requests (>=2.27.1)
Requires-Dist: scikit-learn (>=1.0.1)
Requires-Dist: scipy (>=1.7.1)
Requires-Dist: setuptools (>=57.4.0)
Requires-Dist: shap (>=0.40.0)
Requires-Dist: tqdm (>=4.62.0)
Requires-Dist: xgboost (>=1.5.0)
Requires-Dist: flake8 (>=4.0.0)
Requires-Dist: mypy (==1.0.0)
Requires-Dist: types-chardet
Requires-Dist: types-colorama
Requires-Dist: types-decorator
Requires-Dist: types-psycopg2
Requires-Dist: types-Pygments
Requires-Dist: types-PyMySQL
Requires-Dist: types-python-dateutil
Requires-Dist: types-pytz
Requires-Dist: types-redis
Requires-Dist: types-requests
Requires-Dist: types-setuptools
Requires-Dist: types-six
Requires-Dist: types-urllib3
